nr_documents_app/__init__.py
nr_documents_app/ext.py
nr_documents_app/theme/__init__.py
nr_documents_app/theme/webpack.py
nr_documents_app/theme/assets/semantic-ui/js/nr_documents_app/search/index.js
nr_documents_app/theme/assets/semantic-ui/js/nr_documents_app/ui_components/.gitkeep
nr_documents_app/theme/templates/.gitkeep
nr_documents_app/theme/templates/semantic-ui/invenio_theme/frontpage.html
nr_documents_app-1.0.8.dist-info/LICENSE
nr_documents_app-1.0.8.dist-info/METADATA
nr_documents_app-1.0.8.dist-info/WHEEL
nr_documents_app-1.0.8.dist-info/entry_points.txt
nr_documents_app-1.0.8.dist-info/top_level.txt
nr_documents_app-1.0.8.dist-info/RECORD
