Metadata-Version: 2.1
Name: nr-documents-app
Version: 1.0.8
Summary: Application package for NR documents site
Home-page: https://github.com/Narodni-repozitar/nr-documents-app
Author: Miroslav Bauer
Author-email: bauer@cesnet.cz
License: MIT
Keywords: oarepo ui nr documents
Platform: any
Classifier: Development Status :: 5 - Production/Stable
Requires-Python: >=3.6
Requires-Dist: Babel (>=2.8)
Requires-Dist: Flask (>=2.1.2)
Requires-Dist: importlib-metadata (>=4.11.4)
Requires-Dist: invenio-assets (<1.3.0,>=1.2.7)
Requires-Dist: oarepo-ui (>=4.0.10)
